xpektra/__init__.py
xpektra/projection_operator.py
xpektra/scheme.py
xpektra/space.py
xpektra/spectral_operator.py
xpektra/tensor_operator.py
xpektra/transform.py
xpektra/green_functions/__init__.py
xpektra/green_functions/displacement_based_operators.py
xpektra/green_functions/fourier_galerkin.py
xpektra/green_functions/spatial.py
xpektra/green_functions/tensor.py
xpektra/plotting/__init__.py
xpektra/plotting/colors.py
xpektra/plotting/latex_sans_serif.mplstyle
xpektra/solvers/__init__.py
xpektra/solvers/linear.py
xpektra/solvers/nonlinear.py
xpektra/solvers/petsc_solvers.py
xpektra-0.3.3.dist-info/METADATA
xpektra-0.3.3.dist-info/WHEEL
xpektra-0.3.3.dist-info/licenses/COPYING
xpektra-0.3.3.dist-info/licenses/COPYING.LESSER
xpektra-0.3.3.dist-info/RECORD
