Metadata-Version: 2.4
Name: xpektra
Version: 0.3.3
Summary: Functional programming and differentiable framework for spectral methods
Project-URL: repository, https://gitlab.ethz.ch/compmechmat/research/mohit-pundir/spectralsolver
Author-email: Mohit Pundir <mpundir@ethz.ch>
License-Expression: LGPL-3.0
License-File: COPYING
License-File: COPYING.LESSER
Classifier: Operating System :: OS Independent
Classifier: Programming Language :: Python :: 3
Requires-Python: >=3.11
Requires-Dist: equinox<=0.13.0
Requires-Dist: jax-autovmap>=0.3.0
Requires-Dist: jax==0.8.0
Requires-Dist: numpy
Requires-Dist: scipy
Provides-Extra: dev
Requires-Dist: cmap>=0.6.2; extra == 'dev'
Requires-Dist: commitizen>=4.9.1; extra == 'dev'
Requires-Dist: pytest>=8.4.2; extra == 'dev'
Provides-Extra: docs
Requires-Dist: jupytext>=1.18.1; extra == 'docs'
Requires-Dist: mkdocs-autorefs>=1.4.3; extra == 'docs'
Requires-Dist: mkdocs-include-exclude-files>=0.1.0; extra == 'docs'
Requires-Dist: mkdocs-ipynb>=0.1.1; extra == 'docs'
Requires-Dist: mkdocs-jupyter>=0.25.1; extra == 'docs'
Requires-Dist: mkdocs-material>=9.6.23; extra == 'docs'
Requires-Dist: mkdocs>=1.6.1; extra == 'docs'
Requires-Dist: mkdocstrings-python>=1.18.2; extra == 'docs'
Provides-Extra: examples
Requires-Dist: ipykernel>=6.30.0; extra == 'examples'
Requires-Dist: jaxopt>=0.8.5; extra == 'examples'
Requires-Dist: matplotlib; extra == 'examples'
Requires-Dist: optax>=0.2.6; extra == 'examples'
Requires-Dist: optimistix>=0.0.11; extra == 'examples'
Requires-Dist: scikit-image>=0.25.2; extra == 'examples'
Requires-Dist: tatva; extra == 'examples'
